LICENSE
pynaf/__init__.py
pynaf-2.0.6.dist-info/LICENSE
pynaf-2.0.6.dist-info/WHEEL
pynaf-2.0.6.dist-info/METADATA
pynaf-2.0.6.dist-info/RECORD
