Metadata-Version: 2.1
Name: pynaf
Version: 2.0.6
Summary: Read and create NAF annotation Documents.
Home-page: https://github.com/josubg/pynaf/
License: Apache License 2.0 (APL 2.0)
Keywords: NLP,XML,markup,NAF
Author: Rodrigo Agerri
Author-email: rodrigo.agerri@ehu.es>, Josu Bermudez <josubg@gmail.com
Requires-Python: >=3.8,<4.0
Classifier: Development Status :: 4 - Beta
Classifier: Intended Audience :: Developers
Classifier: Intended Audience :: Science/Research
Classifier: License :: OSI Approved :: Apache Software License
Classifier: License :: Other/Proprietary License
Classifier: Programming Language :: Python :: 3
Classifier: Programming Language :: Python :: 3.8
Classifier: Programming Language :: Python :: 3.9
Classifier: Topic :: Software Development :: Libraries :: Python Modules
Classifier: Topic :: Text Processing :: Markup :: XML
Requires-Dist: lxml (>=4.6.3,<5.0.0)
Project-URL: Repository, https://github.com/josubg/pynaf/
